doex/__init__.py
doex/_version.py
doex/covariance.py
doex/crd.py
doex/graeco_latin_square.py
doex/latin_square.py
doex/rcbd.py
doex/utils.py
doex-0.0.7.dist-info/LICENSE
doex-0.0.7.dist-info/METADATA
doex-0.0.7.dist-info/WHEEL
doex-0.0.7.dist-info/top_level.txt
doex-0.0.7.dist-info/RECORD
