Metadata-Version: 2.1
Name: doex
Version: 0.0.7
Summary: Python library for conducting design of experiments
Home-page: https://github.com/rohitsanj/doex
Author: Rohit Sanjay
Author-email: sanjay.rohit2@gmail.com
License: BSD
Project-URL: Documentation, https://doex.rohitsanjay.com
Project-URL: Source, https://github.com/rohitsanj/doex/
Project-URL: Tracker, https://github.com/rohitsanj/doex/issues
Keywords: design-of-experiments probability statistics
Platform: UNKNOWN
Classifier: Intended Audience :: Developers
Classifier: License :: OSI Approved :: BSD License
Classifier: Programming Language :: Python
Classifier: Programming Language :: Python :: 3
Classifier: Programming Language :: Python :: 3.6
Classifier: Programming Language :: Python :: 3.7
Classifier: Programming Language :: Python :: 3.8
Requires-Python: >=3.5
Requires-Dist: numpy (>=1.19)
Requires-Dist: scipy (>=1.5)
Requires-Dist: prettytable (>=1.0.1)
Requires-Dist: statsmodels (>=0.12.0)
Provides-Extra: dev
Requires-Dist: codecov ; extra == 'dev'
Requires-Dist: coverage ; extra == 'dev'
Requires-Dist: pytest (>=4.1) ; extra == 'dev'
Requires-Dist: pytest-cov (>=2.6.1) ; extra == 'dev'
Requires-Dist: check-manifest ; extra == 'dev'
Requires-Dist: flake8 ; extra == 'dev'
Requires-Dist: tox ; extra == 'dev'
Requires-Dist: bumpversion ; extra == 'dev'
Requires-Dist: xmltodict ; extra == 'dev'
Requires-Dist: pip (>=18.1) ; extra == 'dev'
Requires-Dist: wheel (>=0.31.0) ; extra == 'dev'
Requires-Dist: setuptools (>=38.6.0) ; extra == 'dev'
Requires-Dist: twine (>=1.11.0) ; extra == 'dev'
Requires-Dist: black ; (python_version >= "3.6") and extra == 'dev'
Provides-Extra: sphinx
Requires-Dist: Sphinx ; extra == 'sphinx'
Requires-Dist: myst-parser ; extra == 'sphinx'
Requires-Dist: furo ; extra == 'sphinx'
Provides-Extra: test
Requires-Dist: codecov ; extra == 'test'
Requires-Dist: coverage ; extra == 'test'
Requires-Dist: pytest (>=4.1) ; extra == 'test'
Requires-Dist: pytest-cov (>=2.6.1) ; extra == 'test'
Requires-Dist: check-manifest ; extra == 'test'
Requires-Dist: flake8 ; extra == 'test'
Requires-Dist: tox ; extra == 'test'
Requires-Dist: bumpversion ; extra == 'test'
Requires-Dist: xmltodict ; extra == 'test'
Requires-Dist: pip (>=18.1) ; extra == 'test'
Requires-Dist: wheel (>=0.31.0) ; extra == 'test'
Requires-Dist: setuptools (>=38.6.0) ; extra == 'test'
Requires-Dist: twine (>=1.11.0) ; extra == 'test'
Requires-Dist: black ; (python_version >= "3.6") and extra == 'test'
